FaceMasque/Classfication_of_Person_with_or_without_Wearing_Mask.py
FaceMasque/Copy of ultra_light_640.onnx
FaceMasque/Copy_of_ultra_light_640.onnx
FaceMasque/__init__.py
FaceMasque/vgg_mask.h5
FaceMasque-1.0.7.dist-info/LICENSE
FaceMasque-1.0.7.dist-info/METADATA
FaceMasque-1.0.7.dist-info/WHEEL
FaceMasque-1.0.7.dist-info/top_level.txt
FaceMasque-1.0.7.dist-info/RECORD
