Metadata-Version: 2.1
Name: FaceMasque
Version: 1.0.7
Summary: A Python package to classify weather a person is weared a mask or not.
Home-page: https://github.com/Kushal0189/FaceMasque
Author: KUSHAL MASTER
Author-email: kushalmaster8@gmail.com
License: UNKNOWN
Platform: UNKNOWN
Classifier: Programming Language :: Python :: 3
Classifier: License :: OSI Approved :: MIT License
Classifier: Operating System :: OS Independent
Requires-Python: >=3.6
Requires-Dist: onnx (==1.6.0)
Requires-Dist: onnx-tf (==1.3.0)
Requires-Dist: onnxruntime (==0.5.0)
Requires-Dist: opencv-python (==4.1.1.26)
Requires-Dist: tensorflow (==1.15.2)
Requires-Dist: keras
